fishknn/__init__.py
fishknn/predict.py
seokxkyu_fishknn-1.0.1.dist-info/METADATA
seokxkyu_fishknn-1.0.1.dist-info/WHEEL
seokxkyu_fishknn-1.0.1.dist-info/entry_points.txt
seokxkyu_fishknn-1.0.1.dist-info/top_level.txt
seokxkyu_fishknn-1.0.1.dist-info/RECORD
