Metadata-Version: 2.1
Name: seokxkyu_fishknn
Version: 1.0.1
Summary: Default template for PDM package
Author-email: Seokxkyu <kyuseok000@gmail.com>
License: MIT
Requires-Python: ==3.11.*
Requires-Dist: pandas>=2.2.2
Requires-Dist: scikit-learn>=1.5.1
